ml_bricks/__init__.py
ml_bricks/path_utils/__init__.py
ml_bricks/path_utils/path_utils.py
ml_bricks/subpackage1/__init__.py
ml_bricks/subpackage1/moduleA.py
ml_bricks/subpackage2/__init__.py
ml_bricks/subpackage2/moduleB.py
ml_bricks-0.0.3.dist-info/LICENSE
ml_bricks-0.0.3.dist-info/METADATA
ml_bricks-0.0.3.dist-info/WHEEL
ml_bricks-0.0.3.dist-info/top_level.txt
ml_bricks-0.0.3.dist-info/RECORD
