Metadata-Version: 2.1
Name: ml-bricks
Version: 0.0.3
Summary: Common utils for machine learning, computer vision
Home-page: https://github.com/jerinka/ml_bricks
Author: Jerin K A
Author-email: jerin.electronics@gmail.com
License: UNKNOWN
Download-URL: https://github.com/jerinka/ml_bricks/archive/refs/tags/v0.0.3.tar.gz
Keywords: machine-learning,utils,vision-utils
Platform: UNKNOWN
License-File: LICENSE
Requires-Dist: pytest
Requires-Dist: coverage
